multi_agent_llm/__init__.py
multi_agent_llm/agent_class.py
multi_agent_llm/llm.py
multi_agent_llm/agents/__init__.py
multi_agent_llm/agents/base.py
multi_agent_llm/agents/iteration_of_thought.py
multi_agent_llm-0.1.3.dist-info/LICENSE
multi_agent_llm-0.1.3.dist-info/METADATA
multi_agent_llm-0.1.3.dist-info/WHEEL
multi_agent_llm-0.1.3.dist-info/top_level.txt
multi_agent_llm-0.1.3.dist-info/RECORD
