Metadata-Version: 2.2
Name: multi_agent_llm
Version: 0.1.3
Summary: An LLM Multi-Agent framework.
Author: Agnostiq Inc.
Author-email: contact@agnostiq.ai
Classifier: Development Status :: 3 - Alpha
Classifier: Intended Audience :: Developers
Classifier: Intended Audience :: Education
Classifier: Intended Audience :: Science/Research
Classifier: Programming Language :: Python :: 3 :: Only
Classifier: Operating System :: OS Independent
Classifier: Topic :: Scientific/Engineering :: Artificial Intelligence
Requires-Python: >=3.7
License-File: LICENSE
Requires-Dist: datasets==3.2.0
Requires-Dist: nest-asyncio==1.6.0
Requires-Dist: networkx==3.4.2
Requires-Dist: numpy==1.26.4
Requires-Dist: openai>=1.46.0
Requires-Dist: pandas==2.2.3
Requires-Dist: pydantic==2.9.2
Requires-Dist: rich==13.9.4
Requires-Dist: rouge_score==0.1.2
Requires-Dist: tenacity==9.0.0
Requires-Dist: tqdm==4.67.1
Dynamic: author
Dynamic: author-email
Dynamic: classifier
Dynamic: description
Dynamic: description-content-type
Dynamic: requires-dist
Dynamic: requires-python
Dynamic: summary
